cself_tools/__init__.py
cself_tools/cli.py
cself_tools/mt_resistivity.py
cself_tools-0.3.0.dist-info/licenses/LICENSE
cself_tools-0.3.0.dist-info/METADATA
cself_tools-0.3.0.dist-info/WHEEL
cself_tools-0.3.0.dist-info/top_level.txt
cself_tools-0.3.0.dist-info/RECORD
