Metadata-Version: 2.4
Name: cself_tools
Version: 0.3.0
Summary: 极低频视电阻率数据处理工具
Home-page: https://github.com/chdwql/cself_tools
Author: WANGQinglin
Author-email: WANG Qinglin <chd_wql@qq.com>
License: MIT License
Project-URL: Homepage, https://github.com/chdwql/cself_tools
Project-URL: Bug Tracker, https://github.com/chdwql/cself_tools/issues
Requires-Python: >=3.6
License-File: LICENSE
Dynamic: author
Dynamic: home-page
Dynamic: license-file
Dynamic: requires-python
